{"PH034917001": {"water_access": 0.21881799999999998, "food_tenure": 79.487179, "shelter_informal_settlers_nhts": 2.6258209999999997, "health_center_attendance": 31.554643, "educ_outofschool_all": 19.830028, "work_unemployment": 43.316655, "po_conflict": 0.0, "participation_assembly_attendance": 94.09739300000001, "sp_sss": 97.688146, "he_risk": 0.812846, "shelter_electricity": 3.5010940919999998, "health_center_attendance.1": 31.55464341, "work_farms": 9.079445145, "work_unskilled": 27.11223203, "health_programs": 71.11597374, "sp_philhealth": 71.11597374, "water_toilet": 0.218818381, "shelter_makeshift_nhts": 0.218818381, "food_malnourished": 4.210526, "health_child_death": "", "health_maternal_death": 0.0, "he_flood": 0.0, "he_volcano": 0.0, "he_landslide": 0.0, "he_earthquake": 0.0, "name": "Bagong Sikat"}, "PH034917002": {"water_access": 0.0, "food_tenure": 95.833333, "shelter_informal_settlers_nhts": 0.656455, "health_center_attendance": 50.855188, "educ_outofschool_all": 6.760563, "work_unemployment": 40.703518, "po_conflict": 0.21881799999999998, "participation_assembly_attendance": 94.605199, "sp_sss": 98.773909, "he_risk": 8.881343, "shelter_electricity": 11.59737418, "health_center_attendance.1": 50.85518814, "work_farms": 9.18079096, "work_unskilled": 58.89830508, "health_programs": 55.57986871, "sp_philhealth": 55.57986871, "water_toilet": 0.43763676100000004, "shelter_makeshift_nhts": 1.7505470459999999, "food_malnourished": 1.960784, "health_child_death": "", "health_maternal_death": 3.4482760000000003, "he_flood": 0.0, "he_volcano": 0.0, "he_landslide": 0.0, "he_earthquake": 0.0, "name": "Balante"}, "PH034917003": {"water_access": 0.152672, "food_tenure": 16.304348, "shelter_informal_settlers_nhts": 1.3740459999999999, "health_center_attendance": 62.796209, "educ_outofschool_all": 5.740988, "work_unemployment": 48.413567, "po_conflict": 0.152672, "participation_assembly_attendance": 97.100048, "sp_sss": 97.718705, "he_risk": 21.602388, "shelter_electricity": 12.0610687, "health_center_attendance.1": 62.79620853, "work_farms": 3.2873807, "work_unskilled": 58.11240721, "health_programs": 60.0, "sp_philhealth": 60.0, "water_toilet": 1.832061069, "shelter_makeshift_nhts": 4.961832061, "food_malnourished": 0.96051228, "health_child_death": "", "health_maternal_death": 0.0, "he_flood": 0.0, "he_volcano": 0.0, "he_landslide": 0.0, "he_earthquake": 0.0, "name": "Bantug"}, "PH034917004": {"water_access": 0.0, "food_tenure": 28.191489, "shelter_informal_settlers_nhts": 0.321027, "health_center_attendance": 50.317046000000005, "educ_outofschool_all": 13.294798000000002, "work_unemployment": 41.204437, "po_conflict": 0.16051400000000002, "participation_assembly_attendance": 95.345507, "sp_sss": 98.06659499999999, "he_risk": 8.783032, "shelter_electricity": 7.223113965, "health_center_attendance.1": 50.31704588, "work_farms": 10.242587599999998, "work_unskilled": 50.49415993, "health_programs": 65.8105939, "sp_philhealth": 65.8105939, "water_toilet": 1.6051364369999999, "shelter_makeshift_nhts": 2.0064205459999997, "food_malnourished": 6.2937059, "health_child_death": "", "health_maternal_death": 0.0, "he_flood": 0.0, "he_volcano": 0.0, "he_landslide": 0.0, "he_earthquake": 0.0, "name": "Bical"}, "PH034917005": {"water_access": 0.0, "food_tenure": 1.449275, "shelter_informal_settlers_nhts": 0.0, "health_center_attendance": 65.045342, "educ_outofschool_all": 19.905213, "work_unemployment": 47.78157, "po_conflict": 0.0, "participation_assembly_attendance": 79.03481, "sp_sss": 97.78481, "he_risk": 1.229283, "shelter_electricity": 6.35451505, "health_center_attendance.1": 65.04534213, "work_farms": 14.81481481, "work_unskilled": 48.36601307, "health_programs": 68.22742475, "sp_philhealth": 68.22742475, "water_toilet": 0.334448161, "shelter_makeshift_nhts": 4.515050167, "food_malnourished": 2.4590161, "health_child_death": "", "health_maternal_death": 0.0, "he_flood": 0.0, "he_volcano": 0.0, "he_landslide": 0.0, "he_earthquake": 0.0, "name": "Cabisuculan"}, "PH034917006": {"water_access": 0.0, "food_tenure": 73.015873, "shelter_informal_settlers_nhts": 0.0, "health_center_attendance": 71.195652, "educ_outofschool_all": 6.451613, "work_unemployment": 42.253521, "po_conflict": 5.363985, "participation_assembly_attendance": 83.333333, "sp_sss": 98.611111, "he_risk": 1.534557, "shelter_electricity": 6.513409962000001, "health_center_attendance.1": 71.19565217, "work_farms": 15.07760532, "work_unskilled": 48.11529933, "health_programs": 57.47126437, "sp_philhealth": 57.47126437, "water_toilet": 0.766283525, "shelter_makeshift_nhts": 1.340996169, "food_malnourished": 6.363636, "health_child_death": "", "health_maternal_death": 0.0, "he_flood": 0.0, "he_volcano": 0.0, "he_landslide": 0.0, "he_earthquake": 0.0, "name": "Calabalabaan"}, "PH034917007": {"water_access": 0.0, "food_tenure": 8.108108, "shelter_informal_settlers_nhts": 0.0, "health_center_attendance": 72.678762, "educ_outofschool_all": 10.344828, "work_unemployment": 47.328244, "po_conflict": 0.0, "participation_assembly_attendance": 83.98760300000001, "sp_sss": 98.03719, "he_risk": 8.168708, "shelter_electricity": 5.454545455, "health_center_attendance.1": 72.67876201, "work_farms": 17.39130435, "work_unskilled": 55.07246377, "health_programs": 58.18181818, "sp_philhealth": 58.18181818, "water_toilet": 2.727272727, "shelter_makeshift_nhts": 1.8181818180000002, "food_malnourished": 2.3255811, "health_child_death": "", "health_maternal_death": 0.0, "he_flood": 0.0, "he_volcano": 0.0, "he_landslide": 0.0, "he_earthquake": 0.0, "name": "Calisitan"}, "PH034917008": {"water_access": 0.883392, "food_tenure": 91.304348, "shelter_informal_settlers_nhts": 4.063604, "health_center_attendance": 59.756098, "educ_outofschool_all": 6.832298, "work_unemployment": 47.299935, "po_conflict": 0.0, "participation_assembly_attendance": 92.8125, "sp_sss": 98.34375, "he_risk": 13.01652, "shelter_electricity": 10.24734982, "health_center_attendance.1": 59.75609756, "work_farms": 7.160493827000001, "work_unskilled": 58.88888889, "health_programs": 56.36042403, "sp_philhealth": 56.36042403, "water_toilet": 1.236749117, "shelter_makeshift_nhts": 4.151943463, "food_malnourished": 1.457726, "health_child_death": "", "health_maternal_death": 0.0, "he_flood": 0.0, "he_volcano": 0.0, "he_landslide": 0.0, "he_earthquake": 0.0, "name": "Catalanacan"}, "PH034917009": {"water_access": 0.0, "food_tenure": 94.594595, "shelter_informal_settlers_nhts": 0.680272, "health_center_attendance": 78.227194, "educ_outofschool_all": 20.087335999999997, "work_unemployment": 48.964677, "po_conflict": 0.680272, "participation_assembly_attendance": 93.338884, "sp_sss": 98.001665, "he_risk": 0.437408, "shelter_electricity": 4.081632653, "health_center_attendance.1": 78.22719449, "work_farms": 10.50119332, "work_unskilled": 63.96181384, "health_programs": 67.68707483, "sp_philhealth": 67.68707483, "water_toilet": 8.503401361, "shelter_makeshift_nhts": 2.3809523809999997, "food_malnourished": 0.0, "health_child_death": "", "health_maternal_death": 0.0, "he_flood": 0.0, "he_volcano": 0.0, "he_landslide": 0.0, "he_earthquake": 0.0, "name": "Curva"}, "PH034917010": {"water_access": 0.0, "food_tenure": 78.26087, "shelter_informal_settlers_nhts": 0.346021, "health_center_attendance": 68.859462, "educ_outofschool_all": 21.524664, "work_unemployment": 46.718844, "po_conflict": 0.17301, "participation_assembly_attendance": 93.358491, "sp_sss": 98.18867900000001, "he_risk": 8.784153, "shelter_electricity": 6.747404844, "health_center_attendance.1": 68.85946177, "work_farms": 13.10734463, "work_unskilled": 48.92655367, "health_programs": 74.22145329, "sp_philhealth": 74.22145329, "water_toilet": 1.384083045, "shelter_makeshift_nhts": 2.076124567, "food_malnourished": 2.3026321, "health_child_death": "", "health_maternal_death": 0.0, "he_flood": 0.0, "he_volcano": 0.0, "he_landslide": 0.0, "he_earthquake": 0.0, "name": "Franza"}, "PH034917011": {"water_access": 0.206186, "food_tenure": 86.486486, "shelter_informal_settlers_nhts": 1.4432989999999999, "health_center_attendance": 71.349724, "educ_outofschool_all": 19.52381, "work_unemployment": 45.276163000000004, "po_conflict": 0.618557, "participation_assembly_attendance": 90.084986, "sp_sss": 98.583569, "he_risk": 8.803069, "shelter_electricity": 7.216494845, "health_center_attendance.1": 71.34972403, "work_farms": 13.54581673, "work_unskilled": 46.74634794, "health_programs": 71.13402062, "sp_philhealth": 71.13402062, "water_toilet": 2.268041237, "shelter_makeshift_nhts": 1.134020619, "food_malnourished": 2.6315789, "health_child_death": "", "health_maternal_death": 0.0, "he_flood": 0.0, "he_volcano": 0.0, "he_landslide": 0.0, "he_earthquake": 0.0, "name": "Gabaldon"}, "PH034917012": {"water_access": 0.0, "food_tenure": 0.0, "shelter_informal_settlers_nhts": 3.4146339999999995, "health_center_attendance": 59.20398, "educ_outofschool_all": 25.730994, "work_unemployment": 43.738977, "po_conflict": 0.48780500000000004, "participation_assembly_attendance": 93.08510600000001, "sp_sss": 98.617021, "he_risk": 1.238636, "shelter_electricity": 5.365853659, "health_center_attendance.1": 59.203980099999995, "work_farms": 15.36050157, "work_unskilled": 62.06896552, "health_programs": 59.02439024, "sp_philhealth": 59.02439024, "water_toilet": 0.487804878, "shelter_makeshift_nhts": 2.43902439, "food_malnourished": 4.6296301, "health_child_death": "", "health_maternal_death": 0.0, "he_flood": 0.0, "he_volcano": 0.0, "he_landslide": 0.0, "he_earthquake": 0.0, "name": "Labney"}, "PH034917013": {"water_access": 0.0, "food_tenure": 86.666667, "shelter_informal_settlers_nhts": 1.709402, "health_center_attendance": 25.930941, "educ_outofschool_all": 12.091503, "work_unemployment": 41.841842, "po_conflict": 0.0, "participation_assembly_attendance": 97.272164, "sp_sss": 98.636082, "he_risk": 21.259006, "shelter_electricity": 14.24501425, "health_center_attendance.1": 25.930941100000002, "work_farms": 6.712564544, "work_unskilled": 46.81583477, "health_programs": 64.95726496, "sp_philhealth": 64.95726496, "water_toilet": 7.122507122999999, "shelter_makeshift_nhts": 1.282051282, "food_malnourished": 3.521127, "health_child_death": "", "health_maternal_death": 0.0, "he_flood": 0.0, "he_volcano": 0.0, "he_landslide": 0.0, "he_earthquake": 0.0, "name": "Licaong"}, "PH034917014": {"water_access": 0.0, "food_tenure": 81.333333, "shelter_informal_settlers_nhts": 0.51458, "health_center_attendance": 92.08006999999999, "educ_outofschool_all": 9.552846, "work_unemployment": 47.969052000000005, "po_conflict": 0.17152699999999999, "participation_assembly_attendance": 94.639866, "sp_sss": 98.458961, "he_risk": 0.710892, "shelter_electricity": 9.777015437000001, "health_center_attendance.1": 92.08006963, "work_farms": 10.16109046, "work_unskilled": 59.72738538, "health_programs": 71.52658662, "sp_philhealth": 71.52658662, "water_toilet": 3.6020583189999997, "shelter_makeshift_nhts": 1.114922813, "food_malnourished": 6.5714288, "health_child_death": "", "health_maternal_death": 0.0, "he_flood": 0.0, "he_volcano": 0.0, "he_landslide": 0.001056, "he_earthquake": 0.0, "name": "Linglingay"}, "PH034917016": {"water_access": 0.0, "food_tenure": 14.705882, "shelter_informal_settlers_nhts": 0.9615379999999999, "health_center_attendance": 88.953866, "educ_outofschool_all": 15.129151, "work_unemployment": 43.521898, "po_conflict": 0.48076899999999995, "participation_assembly_attendance": 86.966825, "sp_sss": 98.518957, "he_risk": 1.434766, "shelter_electricity": 12.25961538, "health_center_attendance.1": 88.95386615, "work_farms": 9.369951535, "work_unskilled": 65.58966074, "health_programs": 67.30769231, "sp_philhealth": 67.30769231, "water_toilet": 3.605769231, "shelter_makeshift_nhts": 3.605769231, "food_malnourished": 11.37725, "health_child_death": "", "health_maternal_death": 0.0, "he_flood": 0.0, "he_volcano": 0.0, "he_landslide": 0.001056, "he_earthquake": 0.0, "name": "Mangandingay"}, "PH034917017": {"water_access": 0.19802, "food_tenure": 15.384615, "shelter_informal_settlers_nhts": 3.366337, "health_center_attendance": 23.111511, "educ_outofschool_all": 11.581292, "work_unemployment": 44.270507, "po_conflict": 0.0, "participation_assembly_attendance": 93.877551, "sp_sss": 98.004535, "he_risk": 3.368447, "shelter_electricity": 6.534653465, "health_center_attendance.1": 23.11151079, "work_farms": 9.662921348, "work_unskilled": 42.58426966, "health_programs": 65.74257426, "sp_philhealth": 65.74257426, "water_toilet": 0.198019802, "shelter_makeshift_nhts": 1.0891089109999998, "food_malnourished": 0.80645162, "health_child_death": "", "health_maternal_death": 0.0, "he_flood": 0.0, "he_volcano": 0.0, "he_landslide": 0.0, "he_earthquake": 0.0, "name": "Magtanggol"}, "PH034917018": {"water_access": 0.224215, "food_tenure": 96.42857099999999, "shelter_informal_settlers_nhts": 3.587444, "health_center_attendance": 78.315789, "educ_outofschool_all": 10.300429, "work_unemployment": 50.338983, "po_conflict": 0.0, "participation_assembly_attendance": 97.953909, "sp_sss": 97.93237099999999, "he_risk": 16.60924, "shelter_electricity": 14.34977578, "health_center_attendance.1": 78.31578947, "work_farms": 14.67576792, "work_unskilled": 66.38225256, "health_programs": 65.47085202, "sp_philhealth": 65.47085202, "water_toilet": 5.156950673, "shelter_makeshift_nhts": 7.735426008999999, "food_malnourished": 0.96385539, "health_child_death": "", "health_maternal_death": 1.8867918999999997, "he_flood": 0.0, "he_volcano": 0.0, "he_landslide": 0.0, "he_earthquake": 0.0, "name": "Maligaya"}, "PH034917019": {"water_access": 0.0, "food_tenure": 80.0, "shelter_informal_settlers_nhts": 0.671141, "health_center_attendance": 61.833332999999996, "educ_outofschool_all": 55.434782999999996, "work_unemployment": 42.790698, "po_conflict": 0.671141, "participation_assembly_attendance": 86.782609, "sp_sss": 98.26087, "he_risk": 9.089271, "shelter_electricity": 8.724832215, "health_center_attendance.1": 61.83333333, "work_farms": 28.45528455, "work_unskilled": 39.02439024, "health_programs": 65.10067114, "sp_philhealth": 65.10067114, "water_toilet": 7.382550336, "shelter_makeshift_nhts": 6.040268456000001, "food_malnourished": 1.7543859, "health_child_death": "", "health_maternal_death": 0.0, "he_flood": 0.0, "he_volcano": 0.0, "he_landslide": 0.0, "he_earthquake": 0.0, "name": "Mapangpang"}, "PH034917020": {"water_access": 0.15060199999999999, "food_tenure": 93.023256, "shelter_informal_settlers_nhts": 3.012048, "health_center_attendance": 54.660727, "educ_outofschool_all": 14.789916, "work_unemployment": 42.735896000000004, "po_conflict": 0.301205, "participation_assembly_attendance": 94.207836, "sp_sss": 98.841567, "he_risk": 1.7969380000000001, "shelter_electricity": 5.572289157, "health_center_attendance.1": 54.66072653, "work_farms": 8.282476024, "work_unskilled": 56.32083697, "health_programs": 69.57831325, "sp_philhealth": 69.57831325, "water_toilet": 2.4096385540000003, "shelter_makeshift_nhts": 1.731927711, "food_malnourished": 0.84745759, "health_child_death": "", "health_maternal_death": 3.174603, "he_flood": 0.0, "he_volcano": 0.0, "he_landslide": 0.0, "he_earthquake": 0.0, "name": "Maragol"}, "PH034917021": {"water_access": 0.0, "food_tenure": 78.095238, "shelter_informal_settlers_nhts": 1.327434, "health_center_attendance": 90.979955, "educ_outofschool_all": 18.367347, "work_unemployment": 46.360759, "po_conflict": 0.0, "participation_assembly_attendance": 86.625514, "sp_sss": 98.14814799999999, "he_risk": 1.830687, "shelter_electricity": 8.849557522000001, "health_center_attendance.1": 90.97995546, "work_farms": 11.50442478, "work_unskilled": 52.21238938, "health_programs": 87.16814159, "sp_philhealth": 87.16814159, "water_toilet": 7.96460177, "shelter_makeshift_nhts": 1.10619469, "food_malnourished": 7.0866141, "health_child_death": "", "health_maternal_death": 0.0, "he_flood": 0.0, "he_volcano": 0.0, "he_landslide": 0.0, "he_earthquake": 0.0, "name": "Matingkis"}, "PH034917022": {"water_access": 0.0, "food_tenure": "", "shelter_informal_settlers_nhts": 1.351351, "health_center_attendance": 76.460177, "educ_outofschool_all": 35.106383, "work_unemployment": 45.939675, "po_conflict": 2.027027, "participation_assembly_attendance": 86.348123, "sp_sss": 96.75767900000001, "he_risk": 0.397015, "shelter_electricity": 2.702702703, "health_center_attendance.1": 76.46017699, "work_farms": 24.89270386, "work_unskilled": 46.78111588, "health_programs": 73.64864865, "sp_philhealth": 73.64864865, "water_toilet": 20.94594595, "shelter_makeshift_nhts": 1.013513514, "food_malnourished": 11.25, "health_child_death": "", "health_maternal_death": 0.0, "he_flood": 1e-06, "he_volcano": 0.0, "he_landslide": 0.0, "he_earthquake": 0.0, "name": "Naglabrahan"}, "PH034917024": {"water_access": 0.921659, "food_tenure": 0.0, "shelter_informal_settlers_nhts": 1.6897080000000002, "health_center_attendance": 77.635542, "educ_outofschool_all": 9.007353, "work_unemployment": 44.188538, "po_conflict": 3.533026, "participation_assembly_attendance": 94.778538, "sp_sss": 98.41555600000001, "he_risk": 0.9700790000000001, "shelter_electricity": 9.523809523999999, "health_center_attendance.1": 77.63554217, "work_farms": 11.80422265, "work_unskilled": 54.22264875, "health_programs": 61.75115207, "sp_philhealth": 61.75115207, "water_toilet": 6.144393241, "shelter_makeshift_nhts": 1.152073733, "food_malnourished": 1.3651879999999998, "health_child_death": "", "health_maternal_death": 0.0, "he_flood": 0.0, "he_volcano": 0.0, "he_landslide": 0.0, "he_earthquake": 0.0, "name": "Palusapis"}, "PH034917025": {"water_access": 0.0, "food_tenure": 81.08108100000001, "shelter_informal_settlers_nhts": 3.90625, "health_center_attendance": 82.092555, "educ_outofschool_all": 49.514563, "work_unemployment": 63.25036600000001, "po_conflict": 0.0, "participation_assembly_attendance": 90.654206, "sp_sss": 98.75389399999999, "he_risk": 1.229283, "shelter_electricity": 9.375, "health_center_attendance.1": 82.09255533, "work_farms": 17.92828685, "work_unskilled": 50.19920319, "health_programs": 68.359375, "sp_philhealth": 68.359375, "water_toilet": 1.5625, "shelter_makeshift_nhts": 0.9765625, "food_malnourished": 0.0, "health_child_death": "", "health_maternal_death": 0.0, "he_flood": 0.0, "he_volcano": 0.0, "he_landslide": 0.0, "he_earthquake": 0.0, "name": "Pandalla"}, "PH034917026": {"water_access": 0.0, "food_tenure": "", "shelter_informal_settlers_nhts": 14.814815, "health_center_attendance": 73.741497, "educ_outofschool_all": 8.673469, "work_unemployment": 51.3382, "po_conflict": 0.0, "participation_assembly_attendance": 95.769231, "sp_sss": 97.788462, "he_risk": 24.872652, "shelter_electricity": 19.13580247, "health_center_attendance.1": 73.74149659999999, "work_farms": 0.5, "work_unskilled": 54.5, "health_programs": 63.58024691, "sp_philhealth": 63.58024691, "water_toilet": 1.8518518519999998, "shelter_makeshift_nhts": 12.34567901, "food_malnourished": 17.269079, "health_child_death": "", "health_maternal_death": 0.0, "he_flood": 0.0, "he_volcano": 0.0, "he_landslide": 0.0, "he_earthquake": 0.0, "name": "Poblacion East"}, "PH034917027": {"water_access": 0.497512, "food_tenure": 65.0, "shelter_informal_settlers_nhts": 2.487562, "health_center_attendance": 56.25, "educ_outofschool_all": 7.906977, "work_unemployment": 45.714286, "po_conflict": 0.497512, "participation_assembly_attendance": 95.46773, "sp_sss": 97.751994, "he_risk": 13.575079999999998, "shelter_electricity": 9.452736318, "health_center_attendance.1": 56.25, "work_farms": 1.644736842, "work_unskilled": 62.17105263, "health_programs": 58.20895522, "sp_philhealth": 58.20895522, "water_toilet": 0.0, "shelter_makeshift_nhts": 6.965174128999999, "food_malnourished": 2.7681661, "health_child_death": "", "health_maternal_death": 0.0, "he_flood": 0.0, "he_volcano": 0.0, "he_landslide": 0.0, "he_earthquake": 0.0, "name": "Poblacion North"}, "PH034917028": {"water_access": 0.680272, "food_tenure": "", "shelter_informal_settlers_nhts": 2.040816, "health_center_attendance": 80.125196, "educ_outofschool_all": 3.04878, "work_unemployment": 50.497512, "po_conflict": 0.0, "participation_assembly_attendance": 95.404255, "sp_sss": 97.446809, "he_risk": 16.559281, "shelter_electricity": 10.20408163, "health_center_attendance.1": 80.12519562, "work_farms": 2.5125628140000003, "work_unskilled": 60.8040201, "health_programs": 53.06122449, "sp_philhealth": 53.06122449, "water_toilet": 0.680272109, "shelter_makeshift_nhts": 8.843537415, "food_malnourished": 4.724410099999999, "health_child_death": "", "health_maternal_death": 0.0, "he_flood": 0.0, "he_volcano": 0.0, "he_landslide": 0.0, "he_earthquake": 0.0, "name": "Poblacion South"}, "PH034917029": {"water_access": 0.518135, "food_tenure": "", "shelter_informal_settlers_nhts": 1.036269, "health_center_attendance": 54.956084999999995, "educ_outofschool_all": 8.376963, "work_unemployment": 46.083418, "po_conflict": 0.0, "participation_assembly_attendance": 97.796818, "sp_sss": 97.870257, "he_risk": 16.375408, "shelter_electricity": 7.772020725, "health_center_attendance.1": 54.95608532, "work_farms": 0.754716981, "work_unskilled": 46.03773585, "health_programs": 57.77202073, "sp_philhealth": 57.77202073, "water_toilet": 0.0, "shelter_makeshift_nhts": 4.922279793, "food_malnourished": 1.385681, "health_child_death": "", "health_maternal_death": 0.0, "he_flood": 0.0, "he_volcano": 0.0, "he_landslide": 0.0, "he_earthquake": 0.0, "name": "Poblacion West"}, "PH034917030": {"water_access": 0.0, "food_tenure": 9.090909, "shelter_informal_settlers_nhts": 0.391389, "health_center_attendance": 85.728444, "educ_outofschool_all": 17.61658, "work_unemployment": 46.159218, "po_conflict": 0.195695, "participation_assembly_attendance": 95.698925, "sp_sss": 98.08321600000001, "he_risk": 0.679059, "shelter_electricity": 8.610567515, "health_center_attendance.1": 85.728444, "work_farms": 11.02464332, "work_unskilled": 59.92217899, "health_programs": 67.71037182, "sp_philhealth": 67.71037182, "water_toilet": 2.348336595, "shelter_makeshift_nhts": 1.369863014, "food_malnourished": 1.282051, "health_child_death": "", "health_maternal_death": 0.0, "he_flood": 0.0, "he_volcano": 0.0, "he_landslide": 0.0, "he_earthquake": 0.0, "name": "Rang-ayan"}, "PH034917031": {"water_access": 0.0, "food_tenure": 100.0, "shelter_informal_settlers_nhts": 1.772152, "health_center_attendance": 65.98890899999999, "educ_outofschool_all": 13.268607999999999, "work_unemployment": 45.654083, "po_conflict": 0.506329, "participation_assembly_attendance": 93.292683, "sp_sss": 98.109756, "he_risk": 9.799907000000001, "shelter_electricity": 8.607594937, "health_center_attendance.1": 65.98890943, "work_farms": 12.60096931, "work_unskilled": 51.37318255, "health_programs": 70.88607595, "sp_philhealth": 70.88607595, "water_toilet": 0.759493671, "shelter_makeshift_nhts": 1.64556962, "food_malnourished": 7.602338799999999, "health_child_death": "", "health_maternal_death": 0.0, "he_flood": 0.0, "he_volcano": 0.0, "he_landslide": 0.0, "he_earthquake": 0.0, "name": "Rizal"}, "PH034917032": {"water_access": 0.0, "food_tenure": 100.0, "shelter_informal_settlers_nhts": 1.243781, "health_center_attendance": 64.671362, "educ_outofschool_all": 43.620178, "work_unemployment": 44.206009, "po_conflict": 0.0, "participation_assembly_attendance": 91.30174, "sp_sss": 98.920216, "he_risk": 1.071569, "shelter_electricity": 9.701492537, "health_center_attendance.1": 64.6713615, "work_farms": 9.846153846, "work_unskilled": 62.76923077, "health_programs": 68.15920398, "sp_philhealth": 68.15920398, "water_toilet": 4.726368159, "shelter_makeshift_nhts": 4.850746269, "food_malnourished": 2.840909, "health_child_death": "", "health_maternal_death": 2.3809519, "he_flood": 0.0, "he_volcano": 0.0, "he_landslide": 0.0, "he_earthquake": 0.0, "name": "San Andres"}, "PH034917033": {"water_access": 0.0, "food_tenure": 15.555556, "shelter_informal_settlers_nhts": 1.7274470000000002, "health_center_attendance": 77.34375, "educ_outofschool_all": 29.177719, "work_unemployment": 51.866667, "po_conflict": 0.767754, "participation_assembly_attendance": 94.228994, "sp_sss": 98.476454, "he_risk": 0.421361, "shelter_electricity": 4.6065259119999995, "health_center_attendance.1": 77.34375, "work_farms": 11.21883657, "work_unskilled": 62.88088643, "health_programs": 78.50287908, "sp_philhealth": 78.50287908, "water_toilet": 4.414587332, "shelter_makeshift_nhts": 1.343570058, "food_malnourished": 5.963303099999999, "health_child_death": "", "health_maternal_death": 0.0, "he_flood": 0.0, "he_volcano": 0.0, "he_landslide": 0.0, "he_earthquake": 0.0, "name": "San Antonio"}, "PH034917034": {"water_access": 0.0, "food_tenure": 13.793103, "shelter_informal_settlers_nhts": 1.0706639999999998, "health_center_attendance": 71.293871, "educ_outofschool_all": 27.019499, "work_unemployment": 41.672781, "po_conflict": 0.0, "participation_assembly_attendance": 94.424734, "sp_sss": 97.871262, "he_risk": 9.396453, "shelter_electricity": 5.995717345, "health_center_attendance.1": 71.29387114, "work_farms": 12.83018868, "work_unskilled": 57.10691824, "health_programs": 73.23340471, "sp_philhealth": 73.23340471, "water_toilet": 1.927194861, "shelter_makeshift_nhts": 2.8907922910000003, "food_malnourished": 1.980198, "health_child_death": "", "health_maternal_death": 0.0, "he_flood": 0.0, "he_volcano": 0.0, "he_landslide": 0.0, "he_earthquake": 0.0, "name": "San Felipe"}, "PH034917035": {"water_access": 0.0, "food_tenure": 94.594595, "shelter_informal_settlers_nhts": 2.265372, "health_center_attendance": 42.207792, "educ_outofschool_all": 18.007663, "work_unemployment": 40.041709999999995, "po_conflict": 0.0, "participation_assembly_attendance": 95.279838, "sp_sss": 98.786244, "he_risk": 2.477025, "shelter_electricity": 10.67961165, "health_center_attendance.1": 42.20779221, "work_farms": 4.347826087, "work_unskilled": 56.52173913, "health_programs": 64.72491909, "sp_philhealth": 64.72491909, "water_toilet": 0.970873786, "shelter_makeshift_nhts": 1.9417475730000002, "food_malnourished": 4.895104900000001, "health_child_death": "", "health_maternal_death": 0.0, "he_flood": 0.0, "he_volcano": 0.0, "he_landslide": 0.0, "he_earthquake": 0.0, "name": "Sapang Cawayan"}, "PH034917036": {"water_access": 0.191939, "food_tenure": 6.25, "shelter_informal_settlers_nhts": 0.767754, "health_center_attendance": 93.66515799999999, "educ_outofschool_all": 25.194805, "work_unemployment": 48.561403999999996, "po_conflict": 0.0, "participation_assembly_attendance": 95.019566, "sp_sss": 98.648168, "he_risk": 0.606314, "shelter_electricity": 7.677543186, "health_center_attendance.1": 93.66515837, "work_farms": 9.959072306, "work_unskilled": 59.75443383, "health_programs": 77.92706334, "sp_philhealth": 77.92706334, "water_toilet": 5.37428023, "shelter_makeshift_nhts": 0.8637236079999999, "food_malnourished": 7.421875, "health_child_death": "", "health_maternal_death": 2.173913, "he_flood": 0.0, "he_volcano": 0.0, "he_landslide": 0.001056, "he_earthquake": 0.0, "name": "Villa Isla"}, "PH034917037": {"water_access": 0.821918, "food_tenure": 91.2, "shelter_informal_settlers_nhts": 4.383562, "health_center_attendance": 40.574282000000004, "educ_outofschool_all": 13.881020000000001, "work_unemployment": 38.785047, "po_conflict": 0.0, "participation_assembly_attendance": 90.930054, "sp_sss": 98.616449, "he_risk": 2.091669, "shelter_electricity": 10.95890411, "health_center_attendance.1": 40.57428215, "work_farms": 5.801526718, "work_unskilled": 65.03816794, "health_programs": 66.30136986, "sp_philhealth": 66.30136986, "water_toilet": 1.917808219, "shelter_makeshift_nhts": 1.6438356159999998, "food_malnourished": 0.60606062, "health_child_death": "", "health_maternal_death": 0.0, "he_flood": 0.0, "he_volcano": 0.0, "he_landslide": 0.0, "he_earthquake": 0.0, "name": "Villa Nati"}, "PH034917038": {"water_access": 0.0, "food_tenure": "", "shelter_informal_settlers_nhts": 5.15873, "health_center_attendance": 23.107178, "educ_outofschool_all": 20.853081, "work_unemployment": 38.150289, "po_conflict": 0.0, "participation_assembly_attendance": 84.358707, "sp_sss": 98.852972, "he_risk": 0.957227, "shelter_electricity": 5.555555556, "health_center_attendance.1": 23.10717797, "work_farms": 12.85046729, "work_unskilled": 55.60747664, "health_programs": 57.93650794, "sp_philhealth": 57.93650794, "water_toilet": 0.396825397, "shelter_makeshift_nhts": 2.579365079, "food_malnourished": 12.5, "health_child_death": "", "health_maternal_death": 0.0, "he_flood": 0.0, "he_volcano": 0.0, "he_landslide": 0.0, "he_earthquake": 0.0, "name": "Villa Santos"}, "PH034917040": {"water_access": 0.0, "food_tenure": 0.0, "shelter_informal_settlers_nhts": 1.607717, "health_center_attendance": 85.28974699999999, "educ_outofschool_all": 4.304636, "work_unemployment": 47.880871, "po_conflict": 0.32154299999999997, "participation_assembly_attendance": 96.995995, "sp_sss": 98.130841, "he_risk": 1.0423639999999998, "shelter_electricity": 15.11254019, "health_center_attendance.1": 85.28974740000001, "work_farms": 5.494505495, "work_unskilled": 55.604395600000004, "health_programs": 75.56270096, "sp_philhealth": 75.56270096, "water_toilet": 0.964630225, "shelter_makeshift_nhts": 2.411575563, "food_malnourished": 11.80556, "health_child_death": "", "health_maternal_death": 0.0, "he_flood": 0.0, "he_volcano": 0.0, "he_landslide": 0.0, "he_earthquake": 0.0, "name": "Villa Cuizon"}}