{"PH175108001": {"Water_Prop": 9.234828, "Food_Prop": 73.737374, "Shelter_Prop": 0.791557, "Health_Prop": 32.50591, "Education_Prop": 5.681818, "Work_Prop": 39.254884000000004, "Peace_Prop": 53.430079000000006, "Participation_Prop": 87.916546, "SocialProtection_Prop": 98.985801, "Environment_Prop": 10.759798, "shelter_electricity": 11.34564644, "health_center_attendance": 32.50591017, "work_farms": 34.40538519, "work_unskilled": 33.80703067, "health_programs": 25.46174142, "sp_philhealth": 25.46174142, "water_toilet": 2.242744063, "shelter_makeshift_nhts": 1.121372032, "food_malnourished": 5.96, "health_child_death": "", "health_maternal_death": 1.4285715, "he_flood": 0.0, "he_volcano": 0.0, "he_landslide": 0.047506, "he_earthquake": 0.0, "name": "Adela"}, "PH175108002": {"Water_Prop": 1.255887, "Food_Prop": 94.11764699999999, "Shelter_Prop": 2.511774, "Health_Prop": 5.32223, "Education_Prop": 11.320755, "Work_Prop": 48.418631, "Peace_Prop": 41.601256, "Participation_Prop": 91.181989, "SocialProtection_Prop": 99.437148, "Environment_Prop": 2.862016, "shelter_electricity": 27.78649922, "health_center_attendance": 5.322230268, "work_farms": 28.53957637, "work_unskilled": 52.50836120000001, "health_programs": 44.2700157, "sp_philhealth": 44.2700157, "water_toilet": 33.75196232, "shelter_makeshift_nhts": 0.47095761399999997, "food_malnourished": 5.7600002, "health_child_death": "", "health_maternal_death": 0.0, "he_flood": 0.0, "he_volcano": 0.0, "he_landslide": 0.001584, "he_earthquake": 0.0, "name": "Aguas"}, "PH175108003": {"Water_Prop": 7.036536, "Food_Prop": 82.74647900000001, "Shelter_Prop": 4.330176, "Health_Prop": 36.123749, "Education_Prop": 5.0588239999999995, "Work_Prop": 50.507099, "Peace_Prop": 15.020298, "Participation_Prop": 92.438272, "SocialProtection_Prop": 99.320988, "Environment_Prop": 20.150645, "shelter_electricity": 24.7631935, "health_center_attendance": 36.12374886, "work_farms": 27.76639344, "work_unskilled": 40.77868852, "health_programs": 50.74424899, "sp_philhealth": 50.74424899, "water_toilet": 27.87550744, "shelter_makeshift_nhts": 0.947225981, "food_malnourished": 9.4499998, "health_child_death": "", "health_maternal_death": 0.0, "he_flood": 0.0, "he_volcano": 0.0, "he_landslide": 0.001584, "he_earthquake": 0.0, "name": "Magsikap"}, "PH175108004": {"Water_Prop": 1.140684, "Food_Prop": 85.333333, "Shelter_Prop": 2.851711, "Health_Prop": 39.644847999999996, "Education_Prop": 8.505747, "Work_Prop": 48.724138, "Peace_Prop": 24.049429999999997, "Participation_Prop": 95.931883, "SocialProtection_Prop": 99.24314100000001, "Environment_Prop": 6.218304, "shelter_electricity": 22.62357414, "health_center_attendance": 39.64484823, "work_farms": 29.58977808, "work_unskilled": 46.133154, "health_programs": 51.33079848, "sp_philhealth": 51.33079848, "water_toilet": 24.14448669, "shelter_makeshift_nhts": 1.568441065, "food_malnourished": 2.77, "health_child_death": "", "health_maternal_death": 1.7391304, "he_flood": 0.0, "he_volcano": 0.0, "he_landslide": 0.190024, "he_earthquake": 0.07142899999999999, "name": "Malawaan"}, "PH175108005": {"Water_Prop": 3.386454, "Food_Prop": 84.848485, "Shelter_Prop": 1.992032, "Health_Prop": 7.479103, "Education_Prop": 11.310592, "Work_Prop": 46.450303999999996, "Peace_Prop": 43.027888, "Participation_Prop": 75.567051, "SocialProtection_Prop": 99.164345, "Environment_Prop": 2.299325, "shelter_electricity": 28.68525896, "health_center_attendance": 7.4791025079999995, "work_farms": 19.44444444, "work_unskilled": 61.11111111, "health_programs": 38.24701195, "sp_philhealth": 38.24701195, "water_toilet": 27.88844622, "shelter_makeshift_nhts": 0.199203187, "food_malnourished": 0.5, "health_child_death": "", "health_maternal_death": 0.0, "he_flood": 0.0, "he_volcano": 0.0, "he_landslide": 0.001584, "he_earthquake": 0.0, "name": "Pitogo"}, "PH175108006": {"Water_Prop": 7.427785000000001, "Food_Prop": 0.0, "Shelter_Prop": 3.43879, "Health_Prop": 20.213081, "Education_Prop": 13.768961, "Work_Prop": 45.155039, "Peace_Prop": 8.390646, "Participation_Prop": 95.22091999999999, "SocialProtection_Prop": 99.188458, "Environment_Prop": 3.427854, "shelter_electricity": 22.42090784, "health_center_attendance": 20.21308079, "work_farms": 43.46289753, "work_unskilled": 40.90106007, "health_programs": 50.20632737, "sp_philhealth": 50.20632737, "water_toilet": 20.35763411, "shelter_makeshift_nhts": 0.962861073, "food_malnourished": 81.949997, "health_child_death": "", "health_maternal_death": 3.1746032000000004, "he_flood": 0.0, "he_volcano": 0.0, "he_landslide": 0.001584, "he_earthquake": 0.0, "name": "Rizal"}, "PH175108007": {"Water_Prop": 26.943005, "Food_Prop": 25.555556, "Shelter_Prop": 2.979275, "Health_Prop": 28.796222999999998, "Education_Prop": 4.721030000000001, "Work_Prop": 46.331237, "Peace_Prop": 35.103627, "Participation_Prop": 95.743473, "SocialProtection_Prop": 98.751419, "Environment_Prop": 9.534494, "shelter_electricity": 14.37823834, "health_center_attendance": 28.79622345, "work_farms": 35.859375, "work_unskilled": 26.875, "health_programs": 28.10880829, "sp_philhealth": 28.10880829, "water_toilet": 6.347150259, "shelter_makeshift_nhts": 1.424870466, "food_malnourished": 0.0, "health_child_death": "", "health_maternal_death": 0.0, "he_flood": 0.0, "he_volcano": 0.0, "he_landslide": 0.047506, "he_earthquake": 0.0, "name": "Rumbang"}, "PH175108008": {"Water_Prop": 1.960784, "Food_Prop": 18.518519, "Shelter_Prop": 2.317291, "Health_Prop": 7.0483009999999995, "Education_Prop": 4.964539, "Work_Prop": 51.59843, "Peace_Prop": 27.807487, "Participation_Prop": 90.963089, "SocialProtection_Prop": 98.854476, "Environment_Prop": 4.782819, "shelter_electricity": 16.22103387, "health_center_attendance": 7.048300537, "work_farms": 27.92584009, "work_unskilled": 48.3198146, "health_programs": 46.88057041, "sp_philhealth": 46.88057041, "water_toilet": 28.52049911, "shelter_makeshift_nhts": 0.6238859179999999, "food_malnourished": 9.319999699999999, "health_child_death": "", "health_maternal_death": 0.0, "he_flood": 0.0, "he_volcano": 0.0, "he_landslide": 0.190024, "he_earthquake": 0.0, "name": "Salvacion"}, "PH175108009": {"Water_Prop": 1.7307689999999998, "Food_Prop": 25.454545, "Shelter_Prop": 1.153846, "Health_Prop": 19.270016000000002, "Education_Prop": 4.049844, "Work_Prop": 49.722736, "Peace_Prop": 23.076923, "Participation_Prop": 86.607473, "SocialProtection_Prop": 99.112098, "Environment_Prop": 27.414346999999996, "shelter_electricity": 16.15384615, "health_center_attendance": 19.270015700000002, "work_farms": 42.76960784, "work_unskilled": 28.55392157, "health_programs": 40.19230769, "sp_philhealth": 40.19230769, "water_toilet": 24.42307692, "shelter_makeshift_nhts": 0.480769231, "food_malnourished": 0.0, "health_child_death": "", "health_maternal_death": 0.0, "he_flood": 0.0, "he_volcano": 0.0, "he_landslide": 0.0, "he_earthquake": 0.0, "name": "San Pedro"}, "PH175108010": {"Water_Prop": 0.780234, "Food_Prop": 18.894009, "Shelter_Prop": 0.780234, "Health_Prop": 21.959027, "Education_Prop": 7.564103, "Work_Prop": 44.956918, "Peace_Prop": 7.93238, "Participation_Prop": 91.470003, "SocialProtection_Prop": 99.004834, "Environment_Prop": 20.148104, "shelter_electricity": 16.90507152, "health_center_attendance": 21.95902689, "work_farms": 24.86187845, "work_unskilled": 42.90976059, "health_programs": 46.42392718, "sp_philhealth": 46.42392718, "water_toilet": 23.53706112, "shelter_makeshift_nhts": 0.715214564, "food_malnourished": 10.11, "health_child_death": "", "health_maternal_death": 1.2658228, "he_flood": 0.0, "he_volcano": 0.0, "he_landslide": 0.001584, "he_earthquake": 0.0, "name": "Santo Ni\u00cc\u00b1o"}, "PH175108012": {"Water_Prop": 18.742724, "Food_Prop": 96.153846, "Shelter_Prop": 1.9790450000000002, "Health_Prop": 13.555045999999999, "Education_Prop": 14.193548000000002, "Work_Prop": 44.878438, "Peace_Prop": 47.962747, "Participation_Prop": 95.652174, "SocialProtection_Prop": 99.59514200000001, "Environment_Prop": 13.164776000000002, "shelter_electricity": 43.30616997, "health_center_attendance": 13.55504587, "work_farms": 24.94577007, "work_unskilled": 58.85755604, "health_programs": 28.87077998, "sp_philhealth": 28.87077998, "water_toilet": 20.7217695, "shelter_makeshift_nhts": 0.814901048, "food_malnourished": 4.6399999, "health_child_death": "", "health_maternal_death": 0.0, "he_flood": 0.0, "he_volcano": 0.0, "he_landslide": 0.010293, "he_earthquake": 0.0, "name": "Manoot"}}